{
  "nightly": {
    "description": "nightly",
    "last_updated": "2023-12-21T01:03:07.130Z",
    "latest": false,
    "tags": [
      "nightly",
      "nightly-1.11.3.4163",
      "nightly-e063064"
    ]
  },
  "release": {
    "description": "master",
    "last_updated": "2023-11-26T20:49:49.881Z",
    "latest": true,
    "tags": [
      "release",
      "release-1.10.5.4116",
      "release-074e27c"
    ]
  },
  "testing": {
    "description": "develop",
    "last_updated": "2023-12-24T06:49:05.097Z",
    "latest": false,
    "tags": [
      "testing",
      "testing-1.11.3.4163",
      "testing-12f929d"
    ]
  }
}
