{
  "nightly": {
    "description": "nightly",
    "last_updated": "2024-01-27T01:46:48.978Z",
    "latest": false,
    "tags": [
      "nightly",
      "nightly-1.13.1.4243",
      "nightly-d2ad4a2"
    ]
  },
  "release": {
    "description": "master",
    "last_updated": "2024-01-27T01:47:00.701Z",
    "latest": true,
    "tags": [
      "release",
      "release-1.12.2.4211",
      "release-6c05ed1"
    ]
  },
  "testing": {
    "description": "develop",
    "last_updated": "2024-01-27T00:54:09.921Z",
    "latest": false,
    "tags": [
      "testing",
      "testing-1.12.2.4211",
      "testing-8362e20"
    ]
  }
}
